my_nouns_package/__init__.py
my_nouns_package/data.py
my_nouns_package-0.1.dist-info/METADATA
my_nouns_package-0.1.dist-info/WHEEL
my_nouns_package-0.1.dist-info/top_level.txt
my_nouns_package-0.1.dist-info/RECORD
