Metadata-Version: 2.1
Name: my_nouns_package
Version: 0.1
Summary: A package to load and use a list of nouns.
Home-page: https://github.com/MuhammadshoaibTahir/Punjabipiplibrary
Author: Muhammad Shoaib Tahir
Author-email: shoaibtahir410@gmail.com
Classifier: Programming Language :: Python :: 3
Classifier: License :: OSI Approved :: MIT License
Classifier: Operating System :: OS Independent
